wrap_logger/__init__.py
wrap_logger/__wrap_logger.py
wrap_logger/py.typed
wrap_logger-0.2.1.dist-info/LICENSE.md
wrap_logger-0.2.1.dist-info/METADATA
wrap_logger-0.2.1.dist-info/WHEEL
wrap_logger-0.2.1.dist-info/RECORD
