Metadata-Version: 2.1
Name: wrap-logger
Version: 0.2.1
Summary: A library to wrap around objects and modules in Python and log property accesses and calls
Home-page: https://github.com/MaddyGuthridge/python-wrap-logger
License: MIT
Keywords: log,logger,wrapper,wrap
Author: Maddy Guthridge
Author-email: hdsq@outlook.com.au
Requires-Python: >=3.9,<4.0
Classifier: Development Status :: 4 - Beta
Classifier: Intended Audience :: Developers
Classifier: License :: OSI Approved :: MIT License
Classifier: Operating System :: OS Independent
Classifier: Programming Language :: Python :: 3
Classifier: Programming Language :: Python :: 3.9
Classifier: Programming Language :: Python :: 3.10
Classifier: Programming Language :: Python :: 3.11
Classifier: Programming Language :: Python :: 3.12
Classifier: Topic :: System :: Logging
Classifier: Topic :: Utilities
Classifier: Typing :: Typed
Project-URL: Bug Tracker, https://github.com/MaddyGuthridge/python-wrap-logger/issues
Project-URL: Documentation, https://github.com/MaddyGuthridge/python-wrap-logger
Project-URL: Online Documentation, https://github.com/MaddyGuthridge/python-wrap-logger
Project-URL: Repository, https://github.com/MaddyGuthridge/python-wrap-logger
